[
    {
        "ID": 190,
        "name": "212",
        "longitude": 116.60238655347423,
        "latitude": 40.08244779881723
    },
    {
        "ID": 189,
        "name": "240",
        "longitude": 116.59895951795367,
        "latitude": 40.08823708963387
    },
    {
        "ID": 188,
        "name": "239",
        "longitude": 116.59863612797008,
        "latitude": 40.08844063730596
    },
    {
        "ID": 187,
        "name": "238",
        "longitude": 116.59861367033233,
        "latitude": 40.08869938346115
    },
    {
        "ID": 186,
        "name": "237",
        "longitude": 116.59881129754451,
        "latitude": 40.08891672946535
    },
    {
        "ID": 185,
        "name": "236",
        "longitude": 116.59907180614242,
        "latitude": 40.08905472656528
    },
    {
        "ID": 184,
        "name": "235",
        "longitude": 116.59955239959025,
        "latitude": 40.089047826539606
    },
    {
        "ID": 183,
        "name": "234",
        "longitude": 116.60028451858088,
        "latitude": 40.08902022713936
    },
    {
        "ID": 182,
        "name": "233",
        "longitude": 116.60094028160317,
        "latitude": 40.089092675540954
    },
    {
        "ID": 181,
        "name": "232",
        "longitude": 116.60161401073566,
        "latitude": 40.089175473619015
    },
    {
        "ID": 180,
        "name": "231",
        "longitude": 116.60198231599475,
        "latitude": 40.089209972788254
    },
    {
        "ID": 179,
        "name": "230",
        "longitude": 116.60231468903343,
        "latitude": 40.0893721198868
    },
    {
        "ID": 178,
        "name": "229",
        "longitude": 116.60279528248127,
        "latitude": 40.08936522007093
    },
    {
        "ID": 177,
        "name": "228",
        "longitude": 116.60297494358326,
        "latitude": 40.08924792309328
    },
    {
        "ID": 176,
        "name": "227",
        "longitude": 116.60310519788221,
        "latitude": 40.08900297874771
    },
    {
        "ID": 175,
        "name": "226",
        "longitude": 116.60300638427611,
        "latitude": 40.0887097343486
    },
    {
        "ID": 174,
        "name": "225",
        "longitude": 116.60270994345782,
        "latitude": 40.088554486798245
    },
    {
        "ID": 173,
        "name": "224",
        "longitude": 116.60157807851526,
        "latitude": 40.087367693732325
    },
    {
        "ID": 172,
        "name": "223",
        "longitude": 116.60178918031009,
        "latitude": 40.08671908870827
    },
    {
        "ID": 171,
        "name": "222",
        "longitude": 116.60199579057739,
        "latitude": 40.085428758952226
    },
    {
        "ID": 170,
        "name": "221",
        "longitude": 116.6019868075223,
        "latitude": 40.084752535402046
    },
    {
        "ID": 169,
        "name": "220",
        "longitude": 116.60209011265594,
        "latitude": 40.08408320419831
    },
    {
        "ID": 168,
        "name": "219",
        "longitude": 116.60214850251408,
        "latitude": 40.083689882768006
    },
    {
        "ID": 167,
        "name": "218",
        "longitude": 116.60308274024446,
        "latitude": 40.08332761100325
    },
    {
        "ID": 166,
        "name": "217",
        "longitude": 116.6036082489678,
        "latitude": 40.08329655904729
    },
    {
        "ID": 165,
        "name": "216",
        "longitude": 116.60404841866769,
        "latitude": 40.08306539403753
    },
    {
        "ID": 164,
        "name": "215",
        "longitude": 116.60413375769114,
        "latitude": 40.08263756417126
    },
    {
        "ID": 163,
        "name": "214",
        "longitude": 116.60382833381775,
        "latitude": 40.08244779881723
    },
    {
        "ID": 162,
        "name": "213",
        "longitude": 116.60336121495256,
        "latitude": 40.08238914434665
    },
    {
        "ID": 161,
        "name": "211",
        "longitude": 116.601600536153,
        "latitude": 40.08232359052921
    },
    {
        "ID": 160,
        "name": "210",
        "longitude": 116.60084146799707,
        "latitude": 40.08217522884994
    },
    {
        "ID": 159,
        "name": "209",
        "longitude": 116.6000779083136,
        "latitude": 40.082026866844814
    },
    {
        "ID": 158,
        "name": "208",
        "longitude": 116.59980392513305,
        "latitude": 40.082202831047496
    },
    {
        "ID": 157,
        "name": "207",
        "longitude": 116.5997275691647,
        "latitude": 40.08260651189807
    },
    {
        "ID": 156,
        "name": "206",
        "longitude": 116.5997994336055,
        "latitude": 40.08273072090518
    },
    {
        "ID": 155,
        "name": "205",
        "longitude": 116.59995214554219,
        "latitude": 40.08308609541395
    },
    {
        "ID": 154,
        "name": "602",
        "longitude": 116.60623130105694,
        "latitude": 40.066654107176475
    },
    {
        "ID": 153,
        "name": "603",
        "longitude": 116.60621333494674,
        "latitude": 40.06600530326186
    },
    {
        "ID": 152,
        "name": "604",
        "longitude": 116.60640197910384,
        "latitude": 40.06528056812054
    },
    {
        "ID": 151,
        "name": "605",
        "longitude": 116.60656367409563,
        "latitude": 40.06454892285702
    },
    {
        "ID": 150,
        "name": "411",
        "longitude": 116.61940045983322,
        "latitude": 40.07088153335966
    },
    {
        "ID": 149,
        "name": "322休息区",
        "longitude": 116.61998884994232,
        "latitude": 40.066783459098005
    },
    {
        "ID": 148,
        "name": "M380试车位",
        "longitude": 116.61955317176998,
        "latitude": 40.11102537993045
    },
    {
        "ID": 147,
        "name": "M11",
        "longitude": 116.61978223967502,
        "latitude": 40.10984587957328
    },
    {
        "ID": 146,
        "name": "M10",
        "longitude": 116.61989452786376,
        "latitude": 40.10923197941691
    },
    {
        "ID": 145,
        "name": "M09",
        "longitude": 116.62004723980047,
        "latitude": 40.10839389322095
    },
    {
        "ID": 144,
        "name": "M08",
        "longitude": 116.62013257882391,
        "latitude": 40.10776618398553
    },
    {
        "ID": 143,
        "name": "M07",
        "longitude": 116.62024037548511,
        "latitude": 40.107117774908616
    },
    {
        "ID": 142,
        "name": "M06",
        "longitude": 116.62034368061876,
        "latitude": 40.10649695186947
    },
    {
        "ID": 141,
        "name": "M05",
        "longitude": 116.62043800269731,
        "latitude": 40.10589336843958
    },
    {
        "ID": 140,
        "name": "M04",
        "longitude": 116.62055029088606,
        "latitude": 40.105210450392946
    },
    {
        "ID": 139,
        "name": "M03",
        "longitude": 116.6206356299095,
        "latitude": 40.104586160678366
    },
    {
        "ID": 138,
        "name": "M02",
        "longitude": 116.62073893504315,
        "latitude": 40.1038376952323
    },
    {
        "ID": 137,
        "name": "M01",
        "longitude": 116.6208781723972,
        "latitude": 40.10302023731321
    },
    {
        "ID": 136,
        "name": "1号门",
        "longitude": 116.61881206972424,
        "latitude": 40.10162674191989
    },
    {
        "ID": 135,
        "name": "2号门",
        "longitude": 116.60286265539452,
        "latitude": 40.076851244234376
    },
    {
        "ID": 134,
        "name": "955",
        "longitude": 116.61995740924941,
        "latitude": 40.095697229637196
    },
    {
        "ID": 133,
        "name": "956",
        "longitude": 116.61980918884025,
        "latitude": 40.09656996890169
    },
    {
        "ID": 132,
        "name": "957",
        "longitude": 116.61967444301376,
        "latitude": 40.0974633938538
    },
    {
        "ID": 131,
        "name": "958",
        "longitude": 116.61953969718726,
        "latitude": 40.09832576193703
    },
    {
        "ID": 130,
        "name": "954",
        "longitude": 116.61228138866664,
        "latitude": 40.09761517143523
    },
    {
        "ID": 129,
        "name": "953",
        "longitude": 116.6124206260207,
        "latitude": 40.0967562438055
    },
    {
        "ID": 128,
        "name": "952",
        "longitude": 116.61253740573699,
        "latitude": 40.09586280949525
    },
    {
        "ID": 127,
        "name": "951",
        "longitude": 116.61266316850838,
        "latitude": 40.09517978996344
    },
    {
        "ID": 126,
        "name": "940",
        "longitude": 116.61650791609108,
        "latitude": 40.09249248948214
    },
    {
        "ID": 125,
        "name": "939",
        "longitude": 116.62083325712163,
        "latitude": 40.09072447031007
    },
    {
        "ID": 124,
        "name": "938",
        "longitude": 116.61971935828926,
        "latitude": 40.09060717569342
    },
    {
        "ID": 123,
        "name": "937",
        "longitude": 116.61885698499968,
        "latitude": 40.09051057997379
    },
    {
        "ID": 122,
        "name": "936",
        "longitude": 116.6179946117101,
        "latitude": 40.09041398411596
    },
    {
        "ID": 121,
        "name": "935",
        "longitude": 116.61650342456353,
        "latitude": 40.09029668896
    },
    {
        "ID": 120,
        "name": "934",
        "longitude": 116.61586562765146,
        "latitude": 40.09028288951649
    },
    {
        "ID": 119,
        "name": "933",
        "longitude": 116.61506613574757,
        "latitude": 40.090206992526795
    },
    {
        "ID": 118,
        "name": "932",
        "longitude": 116.6138893555295,
        "latitude": 40.09006209803685
    },
    {
        "ID": 117,
        "name": "931",
        "longitude": 116.61335037222351,
        "latitude": 40.089979301045865
    },
    {
        "ID": 116,
        "name": "637",
        "longitude": 116.60956401449896,
        "latitude": 40.05906650838187
    },
    {
        "ID": 115,
        "name": "636",
        "longitude": 116.60907892952356,
        "latitude": 40.05900093069545
    },
    {
        "ID": 114,
        "name": "635",
        "longitude": 116.60863426829613,
        "latitude": 40.05896986755862
    },
    {
        "ID": 113,
        "name": "634",
        "longitude": 116.60825697998195,
        "latitude": 40.058956061715456
    },
    {
        "ID": 112,
        "name": "633",
        "longitude": 116.60787969166775,
        "latitude": 40.058918095632194
    },
    {
        "ID": 111,
        "name": "632",
        "longitude": 116.60750240335356,
        "latitude": 40.05888358099255
    },
    {
        "ID": 110,
        "name": "631",
        "longitude": 116.60710265740161,
        "latitude": 40.05882490606471
    },
    {
        "ID": 109,
        "name": "630",
        "longitude": 116.60671638603233,
        "latitude": 40.05878693990779
    },
    {
        "ID": 108,
        "name": "629",
        "longitude": 116.6055261312316,
        "latitude": 40.0588007457855
    },
    {
        "ID": 107,
        "name": "628",
        "longitude": 116.60546324984591,
        "latitude": 40.05910447438178
    },
    {
        "ID": 106,
        "name": "627",
        "longitude": 116.60540485998776,
        "latitude": 40.05943926454883
    },
    {
        "ID": 105,
        "name": "626",
        "longitude": 116.60535096165717,
        "latitude": 40.059784407315234
    },
    {
        "ID": 104,
        "name": "625",
        "longitude": 116.60656367409563,
        "latitude": 40.05999839494543
    },
    {
        "ID": 103,
        "name": "624",
        "longitude": 116.60697240310267,
        "latitude": 40.06004671463916
    },
    {
        "ID": 102,
        "name": "623",
        "longitude": 116.60733172530666,
        "latitude": 40.0601329997206
    },
    {
        "ID": 101,
        "name": "622",
        "longitude": 116.60771799667596,
        "latitude": 40.060181319318104
    },
    {
        "ID": 100,
        "name": "608",
        "longitude": 116.60668045381193,
        "latitude": 40.06350148321999
    },
    {
        "ID": 99,
        "name": "609",
        "longitude": 116.60680172505577,
        "latitude": 40.062807782618016
    },
    {
        "ID": 98,
        "name": "610",
        "longitude": 116.60690053866188,
        "latitude": 40.0620830131903
    },
    {
        "ID": 97,
        "name": "611",
        "longitude": 116.60702180990572,
        "latitude": 40.06137894401913
    },
    {
        "ID": 96,
        "name": "612",
        "longitude": 116.60702630143327,
        "latitude": 40.06066106201952
    },
    {
        "ID": 95,
        "name": "564",
        "longitude": 116.62305656325883,
        "latitude": 40.080013596848275
    },
    {
        "ID": 94,
        "name": "565",
        "longitude": 116.62297571576293,
        "latitude": 40.080707120836564
    },
    {
        "ID": 93,
        "name": "563",
        "longitude": 116.62310597006187,
        "latitude": 40.07940632621567
    },
    {
        "ID": 92,
        "name": "562",
        "longitude": 116.62320927519552,
        "latitude": 40.078629977967864
    },
    {
        "ID": 91,
        "name": "561",
        "longitude": 116.62332605491181,
        "latitude": 40.078105506546535
    },
    {
        "ID": 90,
        "name": "560",
        "longitude": 116.62340690240772,
        "latitude": 40.07749821876129
    },
    {
        "ID": 89,
        "name": "556",
        "longitude": 116.61417681329269,
        "latitude": 40.08151794831166
    },
    {
        "ID": 88,
        "name": "555",
        "longitude": 116.61425316926105,
        "latitude": 40.08088308847722
    },
    {
        "ID": 87,
        "name": "554",
        "longitude": 116.61459452535483,
        "latitude": 40.078529914655746
    },
    {
        "ID": 86,
        "name": "553",
        "longitude": 116.61477867798438,
        "latitude": 40.07749476824692
    },
    {
        "ID": 85,
        "name": "552",
        "longitude": 116.61481011867723,
        "latitude": 40.07692543096128
    },
    {
        "ID": 84,
        "name": "551",
        "longitude": 116.61485054242517,
        "latitude": 40.07639749573646
    },
    {
        "ID": 83,
        "name": "536",
        "longitude": 116.61831351016615,
        "latitude": 40.07748096618766
    },
    {
        "ID": 82,
        "name": "535",
        "longitude": 116.61819673044984,
        "latitude": 40.07824007526008
    },
    {
        "ID": 81,
        "name": "534",
        "longitude": 116.6181024083713,
        "latitude": 40.07896812185696
    },
    {
        "ID": 80,
        "name": "533",
        "longitude": 116.61801706934784,
        "latitude": 40.07946843369007
    },
    {
        "ID": 79,
        "name": "532",
        "longitude": 116.61790028963155,
        "latitude": 40.08007570376436
    },
    {
        "ID": 78,
        "name": "531",
        "longitude": 116.61777452686016,
        "latitude": 40.080941744255576
    },
    {
        "ID": 77,
        "name": "530",
        "longitude": 116.6176532556163,
        "latitude": 40.081676662337976
    },
    {
        "ID": 76,
        "name": "529",
        "longitude": 116.61726249271946,
        "latitude": 40.08257028435124
    },
    {
        "ID": 75,
        "name": "528",
        "longitude": 116.61667859413798,
        "latitude": 40.08327413274904
    },
    {
        "ID": 74,
        "name": "527",
        "longitude": 116.6159150344545,
        "latitude": 40.083874468233695
    },
    {
        "ID": 73,
        "name": "526",
        "longitude": 116.61470681354358,
        "latitude": 40.084391994541285
    },
    {
        "ID": 72,
        "name": "525",
        "longitude": 116.61384893178155,
        "latitude": 40.08470250842244
    },
    {
        "ID": 71,
        "name": "524",
        "longitude": 116.61364681304181,
        "latitude": 40.08526487992872
    },
    {
        "ID": 70,
        "name": "523",
        "longitude": 116.61441037272529,
        "latitude": 40.08502682139638
    },
    {
        "ID": 69,
        "name": "522",
        "longitude": 116.61515596629857,
        "latitude": 40.084785311882975
    },
    {
        "ID": 68,
        "name": "521",
        "longitude": 116.6159150344545,
        "latitude": 40.08455760212221
    },
    {
        "ID": 67,
        "name": "520",
        "longitude": 116.61664266191758,
        "latitude": 40.08431954109694
    },
    {
        "ID": 66,
        "name": "519",
        "longitude": 116.6199304600841,
        "latitude": 40.08502337126656
    },
    {
        "ID": 65,
        "name": "518",
        "longitude": 116.62059071463393,
        "latitude": 40.085392534158416
    },
    {
        "ID": 64,
        "name": "517",
        "longitude": 116.62123300307357,
        "latitude": 40.08578929576444
    },
    {
        "ID": 63,
        "name": "516",
        "longitude": 116.62188876609585,
        "latitude": 40.086165354613364
    },
    {
        "ID": 62,
        "name": "515",
        "longitude": 116.62229300357535,
        "latitude": 40.08647241028577
    },
    {
        "ID": 61,
        "name": "514",
        "longitude": 116.62131834209701,
        "latitude": 40.08519932766296
    },
    {
        "ID": 60,
        "name": "513",
        "longitude": 116.62058622310639,
        "latitude": 40.08473010958723
    },
    {
        "ID": 59,
        "name": "512",
        "longitude": 116.61972834134436,
        "latitude": 40.08383306595779
    },
    {
        "ID": 58,
        "name": "511",
        "longitude": 116.61930613775466,
        "latitude": 40.08304296766254
    },
    {
        "ID": 57,
        "name": "510",
        "longitude": 116.61912647665267,
        "latitude": 40.08223215849333
    },
    {
        "ID": 56,
        "name": "509",
        "longitude": 116.61920732414858,
        "latitude": 40.08121777076401
    },
    {
        "ID": 55,
        "name": "508",
        "longitude": 116.61934656150262,
        "latitude": 40.08035518418009
    },
    {
        "ID": 54,
        "name": "507",
        "longitude": 116.61944986663626,
        "latitude": 40.079623702126234
    },
    {
        "ID": 53,
        "name": "505",
        "longitude": 116.61958461246276,
        "latitude": 40.07875419428708
    },
    {
        "ID": 52,
        "name": "503",
        "longitude": 116.61974630745456,
        "latitude": 40.07777425934042
    },
    {
        "ID": 51,
        "name": "501",
        "longitude": 116.61983613800555,
        "latitude": 40.07694958476176
    },
    {
        "ID": 50,
        "name": "409桥头",
        "longitude": 116.61871325611808,
        "latitude": 40.07460662590831
    },
    {
        "ID": 49,
        "name": "407桥头",
        "longitude": 116.62024935854015,
        "latitude": 40.07484472116482
    },
    {
        "ID": 48,
        "name": "401",
        "longitude": 116.62082876559408,
        "latitude": 40.07099023538526
    },
    {
        "ID": 47,
        "name": "301",
        "longitude": 116.62673961584973,
        "latitude": 40.06033318068541
    },
    {
        "ID": 46,
        "name": "302",
        "longitude": 116.6259715646387,
        "latitude": 40.06075770042507
    },
    {
        "ID": 45,
        "name": "303",
        "longitude": 116.62520351342768,
        "latitude": 40.061016552616465
    },
    {
        "ID": 44,
        "name": "304",
        "longitude": 116.6240716484851,
        "latitude": 40.06141345738474
    },
    {
        "ID": 43,
        "name": "305",
        "longitude": 116.62342486851792,
        "latitude": 40.061789651926865
    },
    {
        "ID": 42,
        "name": "306",
        "longitude": 116.62279156313338,
        "latitude": 40.06230734741502
    },
    {
        "ID": 41,
        "name": "307",
        "longitude": 116.62232444426819,
        "latitude": 40.06293547928337
    },
    {
        "ID": 40,
        "name": "308",
        "longitude": 116.621947155954,
        "latitude": 40.06369820299046
    },
    {
        "ID": 39,
        "name": "310",
        "longitude": 116.62179444401731,
        "latitude": 40.0645506487132
    },
    {
        "ID": 38,
        "name": "312",
        "longitude": 116.62166418971836,
        "latitude": 40.065409985948435
    },
    {
        "ID": 37,
        "name": "314",
        "longitude": 116.62156537611226,
        "latitude": 40.06615887735993
    },
    {
        "ID": 36,
        "name": "316",
        "longitude": 116.62139918959292,
        "latitude": 40.06721145264281
    },
    {
        "ID": 35,
        "name": "318",
        "longitude": 116.62133181667967,
        "latitude": 40.067984481098165
    },
    {
        "ID": 34,
        "name": "320",
        "longitude": 116.61973732439945,
        "latitude": 40.06855044275336
    },
    {
        "ID": 33,
        "name": "322",
        "longitude": 116.61985410411576,
        "latitude": 40.067708400522015
    },
    {
        "ID": 32,
        "name": "324",
        "longitude": 116.6200202906351,
        "latitude": 40.066731756432226
    },
    {
        "ID": 31,
        "name": "326",
        "longitude": 116.6201370703514,
        "latitude": 40.06584827824247
    },
    {
        "ID": 30,
        "name": "328",
        "longitude": 116.62024935854015,
        "latitude": 40.06512354141734
    },
    {
        "ID": 29,
        "name": "330",
        "longitude": 116.62038410436664,
        "latitude": 40.06425729815955
    },
    {
        "ID": 28,
        "name": "331",
        "longitude": 116.6204335111697,
        "latitude": 40.06316671317157
    },
    {
        "ID": 27,
        "name": "332",
        "longitude": 116.62026732465034,
        "latitude": 40.06255929111825
    },
    {
        "ID": 26,
        "name": "333",
        "longitude": 116.6199394431392,
        "latitude": 40.06190009396371
    },
    {
        "ID": 25,
        "name": "334",
        "longitude": 116.61955766329746,
        "latitude": 40.06137204134391
    },
    {
        "ID": 24,
        "name": "335",
        "longitude": 116.61877164597622,
        "latitude": 40.060592034502406
    },
    {
        "ID": 23,
        "name": "336",
        "longitude": 116.6180395269856,
        "latitude": 40.06011919411498
    },
    {
        "ID": 22,
        "name": "337",
        "longitude": 116.61741071312862,
        "latitude": 40.059753344538414
    }
]